Metadata-Version: 1.1
Name: SafeAPI
Version: 0.0.5
Summary: A python wrapper around the Safe Launcher API.
Home-page: https://github.com/hintofbasil/PySafeAPI
Author: hintofbasil
Author-email: william@hutcheson.org.uk
License: UNKNOWN
Keywords: Maidsafe Safe API
Platform: UNKNOWN
Classifier: Development Status :: 3 - Alpha
Classifier: Intended Audience :: Developers
Classifier: Programming Language :: Python :: 2
Classifier: Programming Language :: Python :: 2.7
